omnivector/__init__.py
omnivector/abstraction.py
omnivector/embedders.py
omnivector/lancedb.py
omnivector/pgvector.py
omnivector/pinecone.py
omnivector/weaviate.py
omnivector-0.1.1.dist-info/LICENSE
omnivector-0.1.1.dist-info/METADATA
omnivector-0.1.1.dist-info/WHEEL
omnivector-0.1.1.dist-info/entry_points.txt
omnivector-0.1.1.dist-info/top_level.txt
omnivector-0.1.1.dist-info/RECORD
