Metadata-Version: 2.1
Name: omnivector
Version: 0.1.1
Summary: .
Home-page: https://github.com/vinid/omnivector
Author: Audrey Roy Greenfeld
Author-email: audreyr@example.com
License: MIT license
Keywords: omnivector
Classifier: Development Status :: 2 - Pre-Alpha
Classifier: Intended Audience :: Developers
Classifier: License :: OSI Approved :: MIT License
Classifier: Natural Language :: English
Classifier: Programming Language :: Python :: 3
Classifier: Programming Language :: Python :: 3.6
Classifier: Programming Language :: Python :: 3.7
Classifier: Programming Language :: Python :: 3.8
Requires-Python: >=3.6
License-File: LICENSE
Requires-Dist: pinecone-client
Requires-Dist: pandas
Requires-Dist: lancedb
Requires-Dist: pgvector
Requires-Dist: psycopg
